LICENSE
README.md
setup.py
skysampler/__init__.py
skysampler/emulator.py
skysampler/icl.py
skysampler/indexer.py
skysampler/naivekde.py
skysampler/old_emulator.py
skysampler/paths.py
skysampler/pipeline.py
skysampler/postporcess.py
skysampler/utils.py
skysampler.egg-info/PKG-INFO
skysampler.egg-info/SOURCES.txt
skysampler.egg-info/dependency_links.txt
skysampler.egg-info/requires.txt
skysampler.egg-info/top_level.txt
skysampler/extgal/__init__.py
skysampler/extgal/object.py
skysampler/extgal/output.py
skysampler/extgal/sampler.py