Metadata-Version: 2.1
Name: skysampler
Version: 0.1
Summary: Generate random realizations of line-of-sights in optical sky surveys 
Author: Tamas Norbert Varga
Author-email: T.Varga@physik.lmu.de
License-File: LICENSE
